utcformatter/__init__.py
utcformatter-0.1.0.dist-info/DESCRIPTION.rst
utcformatter-0.1.0.dist-info/METADATA
utcformatter-0.1.0.dist-info/RECORD
utcformatter-0.1.0.dist-info/WHEEL
utcformatter-0.1.0.dist-info/metadata.json
utcformatter-0.1.0.dist-info/top_level.txt
