Metadata-Version: 2.0
Name: utcformatter
Version: 0.1.0
Summary: logging.Formatter with UTC timezone
Home-page: https://github.com/czchen/utcformatter
Author: ChangZhuo Chen
Author-email: czchen@czchen.org
License: MIT
Keywords: logging
Platform: UNKNOWN
Classifier: Intended Audience :: Developers
Classifier: License :: OSI Approved :: MIT License
Classifier: Topic :: Software Development :: Libraries :: Python Modules
Classifier: Programming Language :: Python
Classifier: Programming Language :: Python :: 3
